sinnn/Initialisers.py
sinnn/Layers.py
sinnn/Losses.py
sinnn/Metrics.py
sinnn/Model.py
sinnn/Optimisers.py
sinnn/__init__.py
sinnn/utils.py
sinnn-0.0.1.dist-info/LICENSE
sinnn-0.0.1.dist-info/METADATA
sinnn-0.0.1.dist-info/WHEEL
sinnn-0.0.1.dist-info/top_level.txt
sinnn-0.0.1.dist-info/RECORD
