Metadata-Version: 2.1
Name: sinnn
Version: 0.0.1
Summary: Numpy powered neural network library
Home-page: https://github.com/sohaibimran7/sinnn
Author: Sohaib Imran
Author-email: sohaibimran7@gmail.com
License: MIT
Platform: UNKNOWN
Classifier: License :: OSI Approved :: MIT License
Classifier: Programming Language :: Python :: 3.6
Requires-Python: >=3.6
Requires-Dist: numpy
